audacity_scripting/__init__.py
audacity_scripting/__main__.py
audacity_scripting/assets/__init__.py
audacity_scripting/bridge/__init__.py
audacity_scripting/bridge/clip.py
audacity_scripting/bridge/pipe.py
audacity_scripting/bridge/project.py
audacity_scripting/bridge/wrappers.py
audacity_scripting/cli/cli.py
audacity_scripting/cli/config.py
audacity_scripting/core/__init__.py
audacity_scripting/core/app.py
audacity_scripting/utils/__init__.py
audacity_scripting/utils/__version__.py
audacity_scripting/utils/enums.py
audacity_scripting/utils/logger.py
audacity_scripting/utils/version.py
audacity_scripting-1.0.11.dist-info/LICENSE
audacity_scripting-1.0.11.dist-info/METADATA
audacity_scripting-1.0.11.dist-info/WHEEL
audacity_scripting-1.0.11.dist-info/entry_points.txt
audacity_scripting-1.0.11.dist-info/top_level.txt
audacity_scripting-1.0.11.dist-info/RECORD
