Metadata-Version: 2.1
Name: audacity_scripting
Version: 1.0.11
Summary: Audacity Scripting - Python package for automating Audacity
Home-page: https://github.com/unfor19/audacity-scripting
Download-URL: https://github.com/unfor19/audacity-scripting/archive/1.0.11.tar.gz
Author: Meir Gabay
Author-email: unfor19@gmail.com
License: MIT
Project-URL: Documentation, https://github.com/unfor19/audacity-scripting
Keywords: python,audacity,scripting,automation
Platform: any
Classifier: Development Status :: 5 - Production/Stable
Classifier: Intended Audience :: Developers
Classifier: Topic :: Software Development :: Build Tools
Classifier: License :: OSI Approved :: MIT License
Classifier: Programming Language :: Python :: 3.9
Classifier: Operating System :: MacOS
Classifier: Operating System :: Microsoft :: Windows
Requires-Python: ~=3.6
License-File: LICENSE
Requires-Dist: click >=7.1.2
Requires-Dist: wrapt-timeout-decorator >=1.4.0
Requires-Dist: pywin32 >=1.0 ; platform_system == "Windows"
